__pyllhttp.cpython-313-darwin.so
pyllhttp/__init__.py
pyllhttp-6.8.0.data/headers/api.h
pyllhttp-6.8.0.data/headers/llhttp.h
pyllhttp-6.8.0.dist-info/LICENSE
pyllhttp-6.8.0.dist-info/METADATA
pyllhttp-6.8.0.dist-info/WHEEL
pyllhttp-6.8.0.dist-info/top_level.txt
pyllhttp-6.8.0.dist-info/RECORD
