Metadata-Version: 2.2
Name: pyllhttp
Version: 6.8.0
Summary: llhttp in python
Home-page: http://github.com/domysh/pyllhttp
Author: Derrick Lyndon Pallas, Domingo Dirutigliano
Author-email: derrick@pallas.us
License: MIT
Keywords: http parser
Classifier: Development Status :: 4 - Beta
Classifier: Programming Language :: Python :: 3 :: Only
Classifier: Programming Language :: JavaScript
Classifier: Topic :: Software Development :: Libraries :: Python Modules
Classifier: Topic :: System :: Networking
Classifier: Topic :: Internet :: WWW/HTTP :: HTTP Servers
Classifier: License :: OSI Approved :: MIT License
License-File: LICENSE
Dynamic: author
Dynamic: author-email
Dynamic: classifier
Dynamic: description
Dynamic: description-content-type
Dynamic: home-page
Dynamic: keywords
Dynamic: license
Dynamic: summary
